AYlib/AYserial.py
AYlib/AYserial_improved.py
AYlib/AYsocket.py
AYlib/AYsql.py
AYlib/AYui.py
AYlib/__init__.py
AYlib/config.py
AYlib-0.0.7.dist-info/LICENSE
AYlib-0.0.7.dist-info/METADATA
AYlib-0.0.7.dist-info/WHEEL
AYlib-0.0.7.dist-info/top_level.txt
AYlib-0.0.7.dist-info/RECORD
