Metadata-Version: 2.1
Name: AYlib
Version: 0.0.7
Summary: A comprehensive Python utility library for network communication, serial communication, database operations, and data visualization
Home-page: https://github.com/AaronYang233/AYlib
Author: Aaron Yang
Author-email: 3300390005@qq.com
License: GNU3.0 License
Keywords: socket,serial,database,ui,utilities
Classifier: Development Status :: 4 - Beta
Classifier: Intended Audience :: Developers
Classifier: Programming Language :: Python :: 3
Classifier: Programming Language :: Python :: 3.7
Classifier: Programming Language :: Python :: 3.8
Classifier: Programming Language :: Python :: 3.9
Classifier: Programming Language :: Python :: 3.10
Classifier: Programming Language :: Python :: 3.11
Classifier: Programming Language :: Python :: 3.12
Classifier: Operating System :: OS Independent
Classifier: Topic :: Software Development :: Libraries :: Python Modules
Requires-Python: >=3.7
License-File: LICENSE
Requires-Dist: pyserial>=3.0
Requires-Dist: requests>=2.20.0
Requires-Dist: matplotlib>=3.0.0
Requires-Dist: numpy>=1.15.0
Requires-Dist: PyMySQL>=0.9.0
Requires-Dist: crcmod>=1.7
